django_io/__init__.py
django_io/admin.py
django_io/fields.py
django_io/importers.py
django_io/views.py
django_io/templates/django_io/upload_data.html
django_io/templates/django_io/admin/change_list.html
django_io/templates/django_io/components/errors.html
tests/__init__.py
django_io-0.1.0.dist-info/LICENSE
django_io-0.1.0.dist-info/METADATA
django_io-0.1.0.dist-info/WHEEL
django_io-0.1.0.dist-info/top_level.txt
django_io-0.1.0.dist-info/RECORD
